[
  {
    "id": 1,
    "unidade": "ULOG",
    "marca": "3M",
    "embalagem": "Caixa",
    "codigo_master": "MAT001",
    "codigo_aghu_hu": "HU12345",
    "codigo_aghu_meac": "ME67890",
    "catmat": "123456",
    "codigo_ebserh": "EB001",
    "descricao": "Luvas de procedimento não estéreis, látex, tamanho M",
    "apresentacao": "Caixa com 100 unidades",
    "classificacao_xyz": "X",
    "comprador_id": 1,
    "controlador_id": 2,
    "processo_id": 1,
    "observacao": "Item de alta rotatividade",
    "comprador_nome": "João Silva",
    "controlador_nome": "Maria Santos",
    "processo_numero": "23076.001234/2024-01"
  },
  {
    "id": 2,
    "unidade": "UACE",
    "marca": "Johnson & Johnson",
    "embalagem": "Frasco",
    "codigo_master": "MED002",
    "codigo_aghu_hu": "HU23456",
    "codigo_aghu_meac": "ME78901",
    "catmat": "234567",
    "codigo_ebserh": "EB002",
    "descricao": "Soro fisiológico 0,9% - 500ml",
    "apresentacao": "Frasco 500ml",
    "classificacao_xyz": "Y",
    "comprador_id": 2,
    "controlador_id": 1,
    "processo_id": 2,
    "observacao": "Medicamento essencial",
    "comprador_nome": "Maria Santos",
    "controlador_nome": "João Silva",
    "processo_numero": "23076.005678/2024-02"
  },
  {
    "id": 3,
    "unidade": "ULOG",
    "marca": "BD",
    "embalagem": "Pacote",
    "codigo_master": "MAT003",
    "codigo_aghu_hu": "HU34567",
    "codigo_aghu_meac": "ME89012",
    "catmat": "345678",
    "codigo_ebserh": "EB003",
    "descricao": "Seringa descartável 10ml com agulha",
    "apresentacao": "Pacote com 50 unidades",
    "classificacao_xyz": "X",
    "comprador_id": 3,
    "controlador_id": 4,
    "processo_id": 1,
    "observacao": "Material cirúrgico",
    "comprador_nome": "Pedro Oliveira",
    "controlador_nome": "Ana Costa",
    "processo_numero": "23076.001234/2024-01"
  },
  {
    "id": 4,
    "unidade": "UACE",
    "marca": "Fresenius",
    "embalagem": "Bolsa",
    "codigo_master": "MED004",
    "codigo_aghu_hu": "HU45678",
    "codigo_aghu_meac": "ME90123",
    "catmat": "456789",
    "codigo_ebserh": "EB004",
    "descricao": "Solução glicosada 5% - 1000ml",
    "apresentacao": "Bolsa 1000ml",
    "classificacao_xyz": "Y",
    "comprador_id": 1,
    "controlador_id": 3,
    "processo_id": 3,
    "observacao": "Para hidratação venosa",
    "comprador_nome": "João Silva",
    "controlador_nome": "Carlos Ferreira",
    "processo_numero": "23076.009012/2024-03"
  },
  {
    "id": 5,
    "unidade": "ULOG",
    "marca": "Medline",
    "embalagem": "Rolo",
    "codigo_master": "MAT005",
    "codigo_aghu_hu": "HU56789",
    "codigo_aghu_meac": null,
    "catmat": "567890",
    "codigo_ebserh": "EB005",
    "descricao": "Atadura de crepe 10cm x 4,5m",
    "apresentacao": "Rolo individual",
    "classificacao_xyz": "Z",
    "comprador_id": 2,
    "controlador_id": 1,
    "processo_id": 2,
    "observacao": null,
    "comprador_nome": "Maria Santos",
    "controlador_nome": "João Silva",
    "processo_numero": "23076.005678/2024-02"
  },
  {
    "id": 6,
    "unidade": "UACE",
    "marca": "Roche",
    "embalagem": "Ampola",
    "codigo_master": "MED006",
    "codigo_aghu_hu": "HU67890",
    "codigo_aghu_meac": "ME01234",
    "catmat": "678901",
    "codigo_ebserh": "EB006",
    "descricao": "Dipirona sódica 500mg/ml - ampola 2ml",
    "apresentacao": "Ampola 2ml",
    "classificacao_xyz": "X",
    "comprador_id": 4,
    "controlador_id": 2,
    "processo_id": 1,
    "observacao": "Analgésico e antitérmico",
    "comprador_nome": "Ana Costa",
    "controlador_nome": "Maria Santos",
    "processo_numero": "23076.001234/2024-01"
  },
  {
    "id": 7,
    "unidade": "ULOG",
    "marca": "Cremer",
    "embalagem": "Pacote",
    "codigo_master": "MAT007",
    "codigo_aghu_hu": "HU78901",
    "codigo_aghu_meac": "ME12345",
    "catmat": "789012",
    "codigo_ebserh": "EB007",
    "descricao": "Gaze estéril 7,5x7,5cm",
    "apresentacao": "Pacote com 10 unidades",
    "classificacao_xyz": "Y",
    "comprador_id": 3,
    "controlador_id": 5,
    "processo_id": 2,
    "observacao": "Material para curativo",
    "comprador_nome": "Pedro Oliveira",
    "controlador_nome": "Carlos Ferreira",
    "processo_numero": "23076.005678/2024-02"
  },
  {
    "id": 8,
    "unidade": "UACE",
    "marca": "Baxter",
    "embalagem": "Frasco",
    "codigo_master": "MED008",
    "codigo_aghu_hu": null,
    "codigo_aghu_meac": "ME23456",
    "catmat": "890123",
    "codigo_ebserh": "EB008",
    "descricao": "Ringer lactato - 500ml",
    "apresentacao": "Frasco 500ml",
    "classificacao_xyz": "Y",
    "comprador_id": 1,
    "controlador_id": 4,
    "processo_id": 3,
    "observacao": "Solução eletrolítica",
    "comprador_nome": "João Silva",
    "controlador_nome": "Ana Costa",
    "processo_numero": "23076.009012/2024-03"
  },
  {
    "id": 9,
    "unidade": "ULOG",
    "marca": "Braun",
    "embalagem": "Unidade",
    "codigo_master": "MAT009",
    "codigo_aghu_hu": "HU89012",
    "codigo_aghu_meac": "ME34567",
    "catmat": "901234",
    "codigo_ebserh": "EB009",
    "descricao": "Cateter venoso periférico 22G",
    "apresentacao": "Unidade estéril",
    "classificacao_xyz": "X",
    "comprador_id": 5,
    "controlador_id": 2,
    "processo_id": 1,
    "observacao": "Para acesso venoso",
    "comprador_nome": "Carlos Ferreira",
    "controlador_nome": "Maria Santos",
    "processo_numero": "23076.001234/2024-01"
  },
  {
    "id": 10,
    "unidade": "UACE",
    "marca": "Pfizer",
    "embalagem": "Frasco-ampola",
    "codigo_master": "MED010",
    "codigo_aghu_hu": "HU90123",
    "codigo_aghu_meac": "ME45678",
    "catmat": "012345",
    "codigo_ebserh": "EB010",
    "descricao": "Amoxicilina 500mg - frasco-ampola",
    "apresentacao": "Frasco-ampola",
    "classificacao_xyz": "X",
    "comprador_id": 2,
    "controlador_id": 1,
    "processo_id": 2,
    "observacao": "Antibiótico beta-lactâmico",
    "comprador_nome": "Maria Santos",
    "controlador_nome": "João Silva",
    "processo_numero": "23076.005678/2024-02"
  }
]